abuseipdb_mcp/__init__.py
abuseipdb_mcp/__main__.py
abuseipdb_mcp-0.0.4.dist-info/METADATA
abuseipdb_mcp-0.0.4.dist-info/WHEEL
abuseipdb_mcp-0.0.4.dist-info/entry_points.txt
abuseipdb_mcp-0.0.4.dist-info/licenses/LICENSE
abuseipdb_mcp-0.0.4.dist-info/RECORD
