Metadata-Version: 2.4
Name: abuseipdb_mcp
Version: 0.0.4
Summary: A MCP for AbuseIPDB API
Project-URL: Homepage, https://github.com/gogela/abuseipdb_mcp
Project-URL: Issues, https://github.com/gogela/abuseipdb_mcp/issues
License-Expression: MIT
License-File: LICENSE
Classifier: Operating System :: OS Independent
Classifier: Programming Language :: Python :: 3
Requires-Python: >=3.8
